departed/__init__.py
departed/_ptrace.py
departed/_ptranspose.py
departed/_utils.py
departed-0.3.1.dist-info/LICENSE
departed-0.3.1.dist-info/METADATA
departed-0.3.1.dist-info/WHEEL
departed-0.3.1.dist-info/top_level.txt
departed-0.3.1.dist-info/RECORD
