Metadata-Version: 2.1
Name: departed
Version: 0.3.1
Summary: Partial trace and partial transpose for matrices with Kronecker product structure.
Home-page: https://provaznik.pro/departed
Author: Jan Provaznik
Author-email: jan@provaznik.pro
License: LGPL
License-File: LICENSE
